PyDbMixinLib/__init__.py
PyDbMixinLib/mixin.py
PyDbMixinLib-0.1.dist-info/METADATA
PyDbMixinLib-0.1.dist-info/WHEEL
PyDbMixinLib-0.1.dist-info/top_level.txt
PyDbMixinLib-0.1.dist-info/RECORD
