Metadata-Version: 2.1
Name: PyDbMixinLib
Version: 0.1
Summary: A mixin for working with databases in FastAPI using SQLAlchemy.
Home-page: https://github.com/ArtemTaU/PyDbMixinLib
Author: ArtemTaU
Classifier: Programming Language :: Python :: 3.11
Classifier: Framework :: FastAPI
Classifier: License :: OSI Approved :: MIT License
Requires-Python: >=3.6
Requires-Dist: fastapi>=0.95.0
Requires-Dist: sqlalchemy>=1.4
